{
    "wallpaper_list": [
        {
            "wallpaper_id": "100103",
            "link": "None"
        },
        {
            "wallpaper_id": "100104",
            "link": "None"
        },
        {
            "wallpaper_id": "100105",
            "link": "None"
        },
        {
            "wallpaper_id": "100106",
            "link": "None"
        },
        {
            "wallpaper_id": "100107",
            "link": "None"
        },
        {
            "wallpaper_id": "100108",
            "link": "None"
        },
        {
            "wallpaper_id": "100109",
            "link": "None"
        },
        {
            "wallpaper_id": "100110",
            "link": "None"
        },
        {
            "wallpaper_id": "100111",
            "link": "None"
        },
        {
            "wallpaper_id": "100112",
            "link": "None"
        },
        {
            "wallpaper_id": "100113",
            "link": "None"
        },
        {
            "wallpaper_id": "100114",
            "link": "None"
        },
        {
            "wallpaper_id": "100115",
            "link": "None"
        },
        {
            "wallpaper_id": "100116",
            "link": "None"
        },
        {
            "wallpaper_id": "100117",
            "link": "None"
        },
        {
            "wallpaper_id": "100118",
            "link": "None"
        },
        {
            "wallpaper_id": "100119",
            "link": "None"
        },
        {
            "wallpaper_id": "100120",
            "link": "None"
        },
        {
            "wallpaper_id": "100121",
            "link": "None"
        },
        {
            "wallpaper_id": "100122",
            "link": "None"
        },
        {
            "wallpaper_id": "100123",
            "link": "None"
        },
        {
            "wallpaper_id": "100124",
            "link": "None"
        },
        {
            "wallpaper_id": "100125",
            "link": "None"
        },
        {
            "wallpaper_id": "100126",
            "link": "None"
        },
        {
            "wallpaper_id": "100127",
            "link": "None"
        },
        {
            "wallpaper_id": "100128",
            "link": "None"
        },
        {
            "wallpaper_id": "100180",
            "link": "None"
        },
        {
            "wallpaper_id": "100181",
            "link": "None"
        },
        {
            "wallpaper_id": "100182",
            "link": "None"
        },
        {
            "wallpaper_id": "100183",
            "link": "None"
        },
        {
            "wallpaper_id": "100184",
            "link": "None"
        },
        {
            "wallpaper_id": "100203",
            "link": "None"
        },
        {
            "wallpaper_id": "100204",
            "link": "None"
        },
        {
            "wallpaper_id": "100205",
            "link": "None"
        },
        {
            "wallpaper_id": "100206",
            "link": "None"
        },
        {
            "wallpaper_id": "100207",
            "link": "None"
        },
        {
            "wallpaper_id": "100208",
            "link": "None"
        },
        {
            "wallpaper_id": "100209",
            "link": "None"
        },
        {
            "wallpaper_id": "100210",
            "link": "None"
        },
        {
            "wallpaper_id": "100211",
            "link": "None"
        },
        {
            "wallpaper_id": "100212",
            "link": "None"
        },
        {
            "wallpaper_id": "100213",
            "link": "None"
        },
        {
            "wallpaper_id": "100214",
            "link": "None"
        },
        {
            "wallpaper_id": "100215",
            "link": "None"
        },
        {
            "wallpaper_id": "100216",
            "link": "None"
        },
        {
            "wallpaper_id": "100217",
            "link": "None"
        },
        {
            "wallpaper_id": "100218",
            "link": "None"
        },
        {
            "wallpaper_id": "100219",
            "link": "None"
        },
        {
            "wallpaper_id": "100220",
            "link": "None"
        },
        {
            "wallpaper_id": "100280",
            "link": "None"
        },
        {
            "wallpaper_id": "100281",
            "link": "None"
        },
        {
            "wallpaper_id": "100282",
            "link": "None"
        },
        {
            "wallpaper_id": "100303",
            "link": "None"
        },
        {
            "wallpaper_id": "100304",
            "link": "None"
        },
        {
            "wallpaper_id": "100305",
            "link": "None"
        },
        {
            "wallpaper_id": "100306",
            "link": "None"
        },
        {
            "wallpaper_id": "100307",
            "link": "None"
        },
        {
            "wallpaper_id": "100308",
            "link": "None"
        },
        {
            "wallpaper_id": "100309",
            "link": "None"
        },
        {
            "wallpaper_id": "100310",
            "link": "None"
        },
        {
            "wallpaper_id": "100311",
            "link": "None"
        },
        {
            "wallpaper_id": "100312",
            "link": "None"
        },
        {
            "wallpaper_id": "100313",
            "link": "None"
        },
        {
            "wallpaper_id": "100314",
            "link": "None"
        },
        {
            "wallpaper_id": "100380",
            "link": "None"
        },
        {
            "wallpaper_id": "100381",
            "link": "None"
        },
        {
            "wallpaper_id": "100382",
            "link": "None"
        },
        {
            "wallpaper_id": "100403",
            "link": "None"
        },
        {
            "wallpaper_id": "100404",
            "link": "None"
        },
        {
            "wallpaper_id": "100405",
            "link": "None"
        },
        {
            "wallpaper_id": "100406",
            "link": "None"
        },
        {
            "wallpaper_id": "100407",
            "link": "None"
        },
        {
            "wallpaper_id": "100408",
            "link": "None"
        },
        {
            "wallpaper_id": "100409",
            "link": "None"
        },
        {
            "wallpaper_id": "100410",
            "link": "None"
        },
        {
            "wallpaper_id": "100411",
            "link": "None"
        },
        {
            "wallpaper_id": "100480",
            "link": "None"
        },
        {
            "wallpaper_id": "100481",
            "link": "None"
        },
        {
            "wallpaper_id": "100503",
            "link": "None"
        },
        {
            "wallpaper_id": "100504",
            "link": "None"
        },
        {
            "wallpaper_id": "100505",
            "link": "None"
        },
        {
            "wallpaper_id": "100506",
            "link": "None"
        },
        {
            "wallpaper_id": "100507",
            "link": "None"
        },
        {
            "wallpaper_id": "100508",
            "link": "None"
        },
        {
            "wallpaper_id": "100509",
            "link": "None"
        },
        {
            "wallpaper_id": "100510",
            "link": "None"
        },
        {
            "wallpaper_id": "100511",
            "link": "None"
        },
        {
            "wallpaper_id": "100512",
            "link": "None"
        },
        {
            "wallpaper_id": "100580",
            "link": "None"
        },
        {
            "wallpaper_id": "100581",
            "link": "None"
        },
        {
            "wallpaper_id": "100582",
            "link": "None"
        },
        {
            "wallpaper_id": "100700",
            "link": "None"
        },
        {
            "wallpaper_id": "100703",
            "link": "None"
        },
        {
            "wallpaper_id": "100704",
            "link": "None"
        },
        {
            "wallpaper_id": "100705",
            "link": "None"
        },
        {
            "wallpaper_id": "100706",
            "link": "None"
        },
        {
            "wallpaper_id": "100707",
            "link": "None"
        },
        {
            "wallpaper_id": "100708",
            "link": "None"
        },
        {
            "wallpaper_id": "100709",
            "link": "None"
        },
        {
            "wallpaper_id": "100710",
            "link": "None"
        },
        {
            "wallpaper_id": "100711",
            "link": "None"
        },
        {
            "wallpaper_id": "100712",
            "link": "None"
        },
        {
            "wallpaper_id": "100713",
            "link": "None"
        },
        {
            "wallpaper_id": "100714",
            "link": "None"
        },
        {
            "wallpaper_id": "100780",
            "link": "None"
        },
        {
            "wallpaper_id": "100781",
            "link": "None"
        },
        {
            "wallpaper_id": "100782",
            "link": "None"
        },
        {
            "wallpaper_id": "100800",
            "link": "None"
        },
        {
            "wallpaper_id": "100803",
            "link": "None"
        },
        {
            "wallpaper_id": "100804",
            "link": "None"
        },
        {
            "wallpaper_id": "100805",
            "link": "None"
        },
        {
            "wallpaper_id": "100806",
            "link": "None"
        },
        {
            "wallpaper_id": "100807",
            "link": "None"
        },
        {
            "wallpaper_id": "100808",
            "link": "None"
        },
        {
            "wallpaper_id": "100809",
            "link": "None"
        },
        {
            "wallpaper_id": "100880",
            "link": "None"
        },
        {
            "wallpaper_id": "100903",
            "link": "None"
        },
        {
            "wallpaper_id": "100904",
            "link": "None"
        },
        {
            "wallpaper_id": "100905",
            "link": "None"
        },
        {
            "wallpaper_id": "100906",
            "link": "None"
        },
        {
            "wallpaper_id": "100907",
            "link": "None"
        },
        {
            "wallpaper_id": "100908",
            "link": "None"
        },
        {
            "wallpaper_id": "100909",
            "link": "None"
        },
        {
            "wallpaper_id": "100910",
            "link": "None"
        },
        {
            "wallpaper_id": "101000",
            "link": "None"
        },
        {
            "wallpaper_id": "101003",
            "link": "None"
        },
        {
            "wallpaper_id": "101004",
            "link": "None"
        },
        {
            "wallpaper_id": "101005",
            "link": "None"
        },
        {
            "wallpaper_id": "101006",
            "link": "None"
        },
        {
            "wallpaper_id": "101007",
            "link": "None"
        },
        {
            "wallpaper_id": "101008",
            "link": "None"
        },
        {
            "wallpaper_id": "101009",
            "link": "None"
        },
        {
            "wallpaper_id": "101103",
            "link": "None"
        },
        {
            "wallpaper_id": "101104",
            "link": "None"
        },
        {
            "wallpaper_id": "101105",
            "link": "None"
        },
        {
            "wallpaper_id": "101106",
            "link": "None"
        },
        {
            "wallpaper_id": "101107",
            "link": "None"
        },
        {
            "wallpaper_id": "101108",
            "link": "None"
        },
        {
            "wallpaper_id": "101109",
            "link": "None"
        },
        {
            "wallpaper_id": "101200",
            "link": "None"
        },
        {
            "wallpaper_id": "101203",
            "link": "None"
        },
        {
            "wallpaper_id": "101204",
            "link": "None"
        },
        {
            "wallpaper_id": "101205",
            "link": "None"
        },
        {
            "wallpaper_id": "101206",
            "link": "None"
        },
        {
            "wallpaper_id": "101207",
            "link": "None"
        },
        {
            "wallpaper_id": "101208",
            "link": "None"
        },
        {
            "wallpaper_id": "101209",
            "link": "None"
        },
        {
            "wallpaper_id": "101210",
            "link": "None"
        },
        {
            "wallpaper_id": "101211",
            "link": "None"
        },
        {
            "wallpaper_id": "101212",
            "link": "None"
        },
        {
            "wallpaper_id": "101303",
            "link": "None"
        },
        {
            "wallpaper_id": "101304",
            "link": "None"
        },
        {
            "wallpaper_id": "101305",
            "link": "None"
        },
        {
            "wallpaper_id": "101306",
            "link": "None"
        },
        {
            "wallpaper_id": "101307",
            "link": "None"
        },
        {
            "wallpaper_id": "101308",
            "link": "None"
        },
        {
            "wallpaper_id": "101309",
            "link": "None"
        },
        {
            "wallpaper_id": "101310",
            "link": "None"
        },
        {
            "wallpaper_id": "101311",
            "link": "None"
        },
        {
            "wallpaper_id": "101312",
            "link": "None"
        },
        {
            "wallpaper_id": "101313",
            "link": "None"
        },
        {
            "wallpaper_id": "101314",
            "link": "None"
        },
        {
            "wallpaper_id": "101315",
            "link": "None"
        },
        {
            "wallpaper_id": "101316",
            "link": "None"
        },
        {
            "wallpaper_id": "101317",
            "link": "None"
        },
        {
            "wallpaper_id": "101318",
            "link": "None"
        },
        {
            "wallpaper_id": "101380",
            "link": "None"
        },
        {
            "wallpaper_id": "101381",
            "link": "None"
        },
        {
            "wallpaper_id": "101382",
            "link": "None"
        },
        {
            "wallpaper_id": "101383",
            "link": "None"
        },
        {
            "wallpaper_id": "101403",
            "link": "None"
        },
        {
            "wallpaper_id": "101405",
            "link": "None"
        },
        {
            "wallpaper_id": "101503",
            "link": "None"
        },
        {
            "wallpaper_id": "101504",
            "link": "None"
        },
        {
            "wallpaper_id": "101505",
            "link": "None"
        },
        {
            "wallpaper_id": "101506",
            "link": "None"
        },
        {
            "wallpaper_id": "101507",
            "link": "None"
        },
        {
            "wallpaper_id": "101603",
            "link": "None"
        },
        {
            "wallpaper_id": "101604",
            "link": "None"
        },
        {
            "wallpaper_id": "101605",
            "link": "None"
        },
        {
            "wallpaper_id": "101606",
            "link": "None"
        },
        {
            "wallpaper_id": "101607",
            "link": "None"
        },
        {
            "wallpaper_id": "101608",
            "link": "None"
        },
        {
            "wallpaper_id": "101609",
            "link": "None"
        },
        {
            "wallpaper_id": "101610",
            "link": "None"
        },
        {
            "wallpaper_id": "101611",
            "link": "None"
        },
        {
            "wallpaper_id": "101612",
            "link": "None"
        },
        {
            "wallpaper_id": "101613",
            "link": "None"
        },
        {
            "wallpaper_id": "101614",
            "link": "None"
        },
        {
            "wallpaper_id": "101703",
            "link": "None"
        },
        {
            "wallpaper_id": "101704",
            "link": "None"
        },
        {
            "wallpaper_id": "101705",
            "link": "None"
        },
        {
            "wallpaper_id": "101706",
            "link": "None"
        },
        {
            "wallpaper_id": "101707",
            "link": "None"
        },
        {
            "wallpaper_id": "101708",
            "link": "None"
        },
        {
            "wallpaper_id": "101803",
            "link": "None"
        },
        {
            "wallpaper_id": "101804",
            "link": "None"
        },
        {
            "wallpaper_id": "101805",
            "link": "None"
        },
        {
            "wallpaper_id": "101806",
            "link": "None"
        },
        {
            "wallpaper_id": "101807",
            "link": "None"
        },
        {
            "wallpaper_id": "101808",
            "link": "None"
        },
        {
            "wallpaper_id": "101809",
            "link": "None"
        },
        {
            "wallpaper_id": "101810",
            "link": "None"
        },
        {
            "wallpaper_id": "101811",
            "link": "None"
        },
        {
            "wallpaper_id": "101900",
            "link": "None"
        },
        {
            "wallpaper_id": "101903",
            "link": "None"
        },
        {
            "wallpaper_id": "101904",
            "link": "None"
        },
        {
            "wallpaper_id": "101905",
            "link": "None"
        },
        {
            "wallpaper_id": "101906",
            "link": "None"
        },
        {
            "wallpaper_id": "101907",
            "link": "None"
        },
        {
            "wallpaper_id": "101908",
            "link": "None"
        },
        {
            "wallpaper_id": "101909",
            "link": "None"
        },
        {
            "wallpaper_id": "101910",
            "link": "None"
        },
        {
            "wallpaper_id": "101911",
            "link": "None"
        },
        {
            "wallpaper_id": "101980",
            "link": "None"
        },
        {
            "wallpaper_id": "101981",
            "link": "None"
        },
        {
            "wallpaper_id": "102000",
            "link": "None"
        },
        {
            "wallpaper_id": "102003",
            "link": "None"
        },
        {
            "wallpaper_id": "102004",
            "link": "None"
        },
        {
            "wallpaper_id": "102005",
            "link": "None"
        },
        {
            "wallpaper_id": "102006",
            "link": "None"
        },
        {
            "wallpaper_id": "102007",
            "link": "None"
        },
        {
            "wallpaper_id": "102008",
            "link": "None"
        },
        {
            "wallpaper_id": "102009",
            "link": "None"
        },
        {
            "wallpaper_id": "102010",
            "link": "None"
        },
        {
            "wallpaper_id": "102011",
            "link": "None"
        },
        {
            "wallpaper_id": "102012",
            "link": "None"
        },
        {
            "wallpaper_id": "102013",
            "link": "None"
        },
        {
            "wallpaper_id": "102103",
            "link": "None"
        },
        {
            "wallpaper_id": "102104",
            "link": "None"
        },
        {
            "wallpaper_id": "102105",
            "link": "None"
        },
        {
            "wallpaper_id": "102106",
            "link": "None"
        },
        {
            "wallpaper_id": "102107",
            "link": "None"
        },
        {
            "wallpaper_id": "102108",
            "link": "None"
        },
        {
            "wallpaper_id": "102109",
            "link": "None"
        },
        {
            "wallpaper_id": "102200",
            "link": "None"
        },
        {
            "wallpaper_id": "102203",
            "link": "None"
        },
        {
            "wallpaper_id": "102204",
            "link": "None"
        },
        {
            "wallpaper_id": "102205",
            "link": "None"
        },
        {
            "wallpaper_id": "102206",
            "link": "None"
        },
        {
            "wallpaper_id": "102207",
            "link": "None"
        },
        {
            "wallpaper_id": "102208",
            "link": "None"
        },
        {
            "wallpaper_id": "102209",
            "link": "None"
        },
        {
            "wallpaper_id": "102280",
            "link": "None"
        },
        {
            "wallpaper_id": "102303",
            "link": "None"
        },
        {
            "wallpaper_id": "102304",
            "link": "None"
        },
        {
            "wallpaper_id": "102305",
            "link": "None"
        },
        {
            "wallpaper_id": "102306",
            "link": "None"
        },
        {
            "wallpaper_id": "102307",
            "link": "None"
        },
        {
            "wallpaper_id": "102308",
            "link": "None"
        },
        {
            "wallpaper_id": "102309",
            "link": "None"
        },
        {
            "wallpaper_id": "102310",
            "link": "None"
        },
        {
            "wallpaper_id": "102311",
            "link": "None"
        },
        {
            "wallpaper_id": "102312",
            "link": "None"
        },
        {
            "wallpaper_id": "102313",
            "link": "None"
        },
        {
            "wallpaper_id": "102403",
            "link": "None"
        },
        {
            "wallpaper_id": "102404",
            "link": "None"
        },
        {
            "wallpaper_id": "102405",
            "link": "None"
        },
        {
            "wallpaper_id": "102406",
            "link": "None"
        },
        {
            "wallpaper_id": "102407",
            "link": "None"
        },
        {
            "wallpaper_id": "102408",
            "link": "None"
        },
        {
            "wallpaper_id": "102409",
            "link": "None"
        },
        {
            "wallpaper_id": "102503",
            "link": "None"
        },
        {
            "wallpaper_id": "102504",
            "link": "None"
        },
        {
            "wallpaper_id": "102505",
            "link": "None"
        },
        {
            "wallpaper_id": "102506",
            "link": "None"
        },
        {
            "wallpaper_id": "102507",
            "link": "None"
        },
        {
            "wallpaper_id": "102508",
            "link": "None"
        },
        {
            "wallpaper_id": "102509",
            "link": "None"
        },
        {
            "wallpaper_id": "102510",
            "link": "None"
        },
        {
            "wallpaper_id": "102701",
            "link": "None"
        },
        {
            "wallpaper_id": "102704",
            "link": "None"
        },
        {
            "wallpaper_id": "102705",
            "link": "None"
        },
        {
            "wallpaper_id": "102706",
            "link": "None"
        },
        {
            "wallpaper_id": "102707",
            "link": "None"
        },
        {
            "wallpaper_id": "102708",
            "link": "None"
        },
        {
            "wallpaper_id": "102709",
            "link": "None"
        },
        {
            "wallpaper_id": "102710",
            "link": "None"
        },
        {
            "wallpaper_id": "102711",
            "link": "None"
        },
        {
            "wallpaper_id": "102712",
            "link": "None"
        },
        {
            "wallpaper_id": "102713",
            "link": "None"
        },
        {
            "wallpaper_id": "102714",
            "link": "None"
        },
        {
            "wallpaper_id": "102801",
            "link": "None"
        },
        {
            "wallpaper_id": "102804",
            "link": "None"
        },
        {
            "wallpaper_id": "102805",
            "link": "None"
        },
        {
            "wallpaper_id": "102806",
            "link": "None"
        },
        {
            "wallpaper_id": "102807",
            "link": "None"
        },
        {
            "wallpaper_id": "102808",
            "link": "None"
        },
        {
            "wallpaper_id": "102809",
            "link": "None"
        },
        {
            "wallpaper_id": "102810",
            "link": "None"
        },
        {
            "wallpaper_id": "102901",
            "link": "None"
        },
        {
            "wallpaper_id": "102904",
            "link": "None"
        },
        {
            "wallpaper_id": "102905",
            "link": "None"
        },
        {
            "wallpaper_id": "102906",
            "link": "None"
        },
        {
            "wallpaper_id": "102907",
            "link": "None"
        },
        {
            "wallpaper_id": "102908",
            "link": "None"
        },
        {
            "wallpaper_id": "102909",
            "link": "None"
        },
        {
            "wallpaper_id": "102910",
            "link": "None"
        },
        {
            "wallpaper_id": "102911",
            "link": "None"
        },
        {
            "wallpaper_id": "102912",
            "link": "None"
        },
        {
            "wallpaper_id": "102913",
            "link": "None"
        },
        {
            "wallpaper_id": "102914",
            "link": "None"
        },
        {
            "wallpaper_id": "102915",
            "link": "None"
        },
        {
            "wallpaper_id": "102916",
            "link": "None"
        },
        {
            "wallpaper_id": "102917",
            "link": "None"
        },
        {
            "wallpaper_id": "102918",
            "link": "None"
        },
        {
            "wallpaper_id": "102919",
            "link": "None"
        },
        {
            "wallpaper_id": "102920",
            "link": "None"
        },
        {
            "wallpaper_id": "102921",
            "link": "None"
        },
        {
            "wallpaper_id": "102922",
            "link": "None"
        },
        {
            "wallpaper_id": "102980",
            "link": "None"
        },
        {
            "wallpaper_id": "102981",
            "link": "None"
        },
        {
            "wallpaper_id": "103001",
            "link": "None"
        },
        {
            "wallpaper_id": "103004",
            "link": "None"
        },
        {
            "wallpaper_id": "103005",
            "link": "None"
        },
        {
            "wallpaper_id": "103006",
            "link": "None"
        },
        {
            "wallpaper_id": "103007",
            "link": "None"
        },
        {
            "wallpaper_id": "103101",
            "link": "None"
        },
        {
            "wallpaper_id": "103104",
            "link": "None"
        },
        {
            "wallpaper_id": "103105",
            "link": "None"
        },
        {
            "wallpaper_id": "103106",
            "link": "None"
        },
        {
            "wallpaper_id": "103107",
            "link": "None"
        },
        {
            "wallpaper_id": "103108",
            "link": "None"
        },
        {
            "wallpaper_id": "103201",
            "link": "None"
        },
        {
            "wallpaper_id": "103204",
            "link": "None"
        },
        {
            "wallpaper_id": "103205",
            "link": "None"
        },
        {
            "wallpaper_id": "103206",
            "link": "None"
        },
        {
            "wallpaper_id": "103207",
            "link": "None"
        },
        {
            "wallpaper_id": "103208",
            "link": "None"
        },
        {
            "wallpaper_id": "103209",
            "link": "None"
        },
        {
            "wallpaper_id": "103210",
            "link": "None"
        },
        {
            "wallpaper_id": "103280",
            "link": "None"
        },
        {
            "wallpaper_id": "103302",
            "link": "None"
        },
        {
            "wallpaper_id": "103304",
            "link": "None"
        },
        {
            "wallpaper_id": "103305",
            "link": "None"
        },
        {
            "wallpaper_id": "103306",
            "link": "None"
        },
        {
            "wallpaper_id": "103307",
            "link": "None"
        },
        {
            "wallpaper_id": "103308",
            "link": "None"
        },
        {
            "wallpaper_id": "103309",
            "link": "None"
        },
        {
            "wallpaper_id": "103310",
            "link": "None"
        },
        {
            "wallpaper_id": "103311",
            "link": "None"
        },
        {
            "wallpaper_id": "103312",
            "link": "None"
        },
        {
            "wallpaper_id": "103313",
            "link": "None"
        },
        {
            "wallpaper_id": "103314",
            "link": "None"
        },
        {
            "wallpaper_id": "103315",
            "link": "None"
        },
        {
            "wallpaper_id": "103316",
            "link": "None"
        },
        {
            "wallpaper_id": "103317",
            "link": "None"
        },
        {
            "wallpaper_id": "103318",
            "link": "None"
        },
        {
            "wallpaper_id": "103319",
            "link": "None"
        },
        {
            "wallpaper_id": "103320",
            "link": "None"
        },
        {
            "wallpaper_id": "103380",
            "link": "None"
        },
        {
            "wallpaper_id": "103381",
            "link": "None"
        },
        {
            "wallpaper_id": "103402",
            "link": "None"
        },
        {
            "wallpaper_id": "103405",
            "link": "None"
        },
        {
            "wallpaper_id": "103406",
            "link": "None"
        },
        {
            "wallpaper_id": "103407",
            "link": "None"
        },
        {
            "wallpaper_id": "103408",
            "link": "None"
        },
        {
            "wallpaper_id": "103409",
            "link": "None"
        },
        {
            "wallpaper_id": "103410",
            "link": "None"
        },
        {
            "wallpaper_id": "103411",
            "link": "None"
        },
        {
            "wallpaper_id": "103412",
            "link": "None"
        },
        {
            "wallpaper_id": "103413",
            "link": "None"
        },
        {
            "wallpaper_id": "103506",
            "link": "None"
        },
        {
            "wallpaper_id": "103507",
            "link": "None"
        },
        {
            "wallpaper_id": "103508",
            "link": "None"
        },
        {
            "wallpaper_id": "103509",
            "link": "None"
        },
        {
            "wallpaper_id": "103510",
            "link": "None"
        },
        {
            "wallpaper_id": "103511",
            "link": "None"
        },
        {
            "wallpaper_id": "103512",
            "link": "None"
        },
        {
            "wallpaper_id": "103513",
            "link": "None"
        },
        {
            "wallpaper_id": "103514",
            "link": "None"
        },
        {
            "wallpaper_id": "103515",
            "link": "None"
        },
        {
            "wallpaper_id": "103516",
            "link": "None"
        },
        {
            "wallpaper_id": "103517",
            "link": "None"
        },
        {
            "wallpaper_id": "103518",
            "link": "None"
        },
        {
            "wallpaper_id": "103519",
            "link": "None"
        },
        {
            "wallpaper_id": "103520",
            "link": "None"
        },
        {
            "wallpaper_id": "103521",
            "link": "None"
        },
        {
            "wallpaper_id": "103602",
            "link": "None"
        },
        {
            "wallpaper_id": "103604",
            "link": "None"
        },
        {
            "wallpaper_id": "103605",
            "link": "None"
        },
        {
            "wallpaper_id": "103606",
            "link": "None"
        },
        {
            "wallpaper_id": "103607",
            "link": "None"
        },
        {
            "wallpaper_id": "103608",
            "link": "None"
        },
        {
            "wallpaper_id": "103609",
            "link": "None"
        },
        {
            "wallpaper_id": "103610",
            "link": "None"
        },
        {
            "wallpaper_id": "103611",
            "link": "None"
        },
        {
            "wallpaper_id": "103702",
            "link": "None"
        },
        {
            "wallpaper_id": "103705",
            "link": "None"
        },
        {
            "wallpaper_id": "103706",
            "link": "None"
        },
        {
            "wallpaper_id": "103707",
            "link": "None"
        },
        {
            "wallpaper_id": "103708",
            "link": "None"
        },
        {
            "wallpaper_id": "103709",
            "link": "None"
        },
        {
            "wallpaper_id": "103710",
            "link": "None"
        },
        {
            "wallpaper_id": "103711",
            "link": "None"
        },
        {
            "wallpaper_id": "103712",
            "link": "None"
        },
        {
            "wallpaper_id": "103713",
            "link": "None"
        },
        {
            "wallpaper_id": "103714",
            "link": "None"
        },
        {
            "wallpaper_id": "103715",
            "link": "None"
        },
        {
            "wallpaper_id": "103716",
            "link": "None"
        },
        {
            "wallpaper_id": "103717",
            "link": "None"
        },
        {
            "wallpaper_id": "103718",
            "link": "None"
        },
        {
            "wallpaper_id": "103719",
            "link": "None"
        },
        {
            "wallpaper_id": "103720",
            "link": "None"
        },
        {
            "wallpaper_id": "103802",
            "link": "None"
        },
        {
            "wallpaper_id": "103805",
            "link": "None"
        },
        {
            "wallpaper_id": "103806",
            "link": "None"
        },
        {
            "wallpaper_id": "103807",
            "link": "None"
        },
        {
            "wallpaper_id": "103808",
            "link": "None"
        },
        {
            "wallpaper_id": "103809",
            "link": "None"
        },
        {
            "wallpaper_id": "103810",
            "link": "None"
        },
        {
            "wallpaper_id": "103811",
            "link": "None"
        },
        {
            "wallpaper_id": "103812",
            "link": "None"
        },
        {
            "wallpaper_id": "103813",
            "link": "None"
        },
        {
            "wallpaper_id": "103814",
            "link": "None"
        },
        {
            "wallpaper_id": "103880",
            "link": "None"
        },
        {
            "wallpaper_id": "103881",
            "link": "None"
        },
        {
            "wallpaper_id": "103902",
            "link": "None"
        },
        {
            "wallpaper_id": "103904",
            "link": "None"
        },
        {
            "wallpaper_id": "103905",
            "link": "None"
        },
        {
            "wallpaper_id": "103906",
            "link": "None"
        },
        {
            "wallpaper_id": "103907",
            "link": "None"
        },
        {
            "wallpaper_id": "103908",
            "link": "None"
        },
        {
            "wallpaper_id": "104002",
            "link": "None"
        },
        {
            "wallpaper_id": "104005",
            "link": "None"
        },
        {
            "wallpaper_id": "104006",
            "link": "None"
        },
        {
            "wallpaper_id": "104007",
            "link": "None"
        },
        {
            "wallpaper_id": "104008",
            "link": "None"
        },
        {
            "wallpaper_id": "104009",
            "link": "None"
        },
        {
            "wallpaper_id": "104010",
            "link": "None"
        },
        {
            "wallpaper_id": "104011",
            "link": "None"
        },
        {
            "wallpaper_id": "104012",
            "link": "None"
        },
        {
            "wallpaper_id": "104102",
            "link": "None"
        },
        {
            "wallpaper_id": "104105",
            "link": "https://1848589192.share.123pan.cn/123pan/UnnAvd-OwngA"
        },
        {
            "wallpaper_id": "104106",
            "link": "https://1848589192.share.123pan.cn/123pan/UnnAvd-1b4gA"
        },
        {
            "wallpaper_id": "104107",
            "link": "https://1848589192.share.123pan.cn/123pan/UnnAvd-4b4gA"
        },
        {
            "wallpaper_id": "104108",
            "link": "https://1848589192.share.123pan.cn/123pan/UnnAvd-OlRwA"
        },
        {
            "wallpaper_id": "104109",
            "link": "https://1848589192.share.123pan.cn/123pan/UnnAvd-IVAgA"
        },
        {
            "wallpaper_id": "104110",
            "link": "https://1848589192.share.123pan.cn/123pan/UnnAvd-xb4gA"
        },
        {
            "wallpaper_id": "104111",
            "link": "https://1848589192.share.123pan.cn/123pan/UnnAvd-MVAgA"
        },
        {
            "wallpaper_id": "104112",
            "link": "https://1848589192.share.123pan.cn/123pan/UnnAvd-wVAgA"
        },
        {
            "wallpaper_id": "104113",
            "link": "https://1848589192.share.123pan.cn/123pan/UnnAvd-tCSwA"
        },
        {
            "wallpaper_id": "104114",
            "link": "https://1848589192.share.123pan.cn/123pan/UnnAvd-RlRwA"
        },
        {
            "wallpaper_id": "104115",
            "link": "https://1848589192.share.123pan.cn/123pan/UnnAvd-jQMwA"
        },
        {
            "wallpaper_id": "104116",
            "link": "https://1848589192.share.123pan.cn/123pan/UnnAvd-RwngA"
        },
        {
            "wallpaper_id": "104117",
            "link": "https://1848589192.share.123pan.cn/123pan/UnnAvd-DkjwA"
        },
        {
            "wallpaper_id": "104180",
            "link": "https://1848589192.share.123pan.cn/123pan/UnnAvd-TEMwA"
        },
        {
            "wallpaper_id": "104181",
            "link": "https://1848589192.share.123pan.cn/123pan/UnnAvd-pb4gA"
        },
        {
            "wallpaper_id": "104182",
            "link": "https://1848589192.share.123pan.cn/123pan/UnnAvd-fb4gA"
        },
        {
            "wallpaper_id": "104183",
            "link": "https://1848589192.share.123pan.cn/123pan/UnnAvd-j6XwA"
        },
        {
            "wallpaper_id": "104184",
            "link": "https://1848589192.share.123pan.cn/123pan/UnnAvd-ab4gA"
        },
        {
            "wallpaper_id": "104185",
            "link": "https://1848589192.share.123pan.cn/123pan/UnnAvd-TOMgA"
        },
        {
            "wallpaper_id": "104186",
            "link": "https://1848589192.share.123pan.cn/123pan/UnnAvd-rkjwA"
        },
        {
            "wallpaper_id": "104202",
            "link": "None"
        },
        {
            "wallpaper_id": "104205",
            "link": "None"
        },
        {
            "wallpaper_id": "104206",
            "link": "None"
        },
        {
            "wallpaper_id": "104207",
            "link": "None"
        },
        {
            "wallpaper_id": "104208",
            "link": "None"
        },
        {
            "wallpaper_id": "104209",
            "link": "None"
        },
        {
            "wallpaper_id": "104210",
            "link": "None"
        },
        {
            "wallpaper_id": "104211",
            "link": "None"
        },
        {
            "wallpaper_id": "104212",
            "link": "None"
        },
        {
            "wallpaper_id": "104213",
            "link": "None"
        },
        {
            "wallpaper_id": "104214",
            "link": "None"
        },
        {
            "wallpaper_id": "104215",
            "link": "None"
        },
        {
            "wallpaper_id": "104216",
            "link": "None"
        },
        {
            "wallpaper_id": "104217",
            "link": "None"
        },
        {
            "wallpaper_id": "104218",
            "link": "None"
        },
        {
            "wallpaper_id": "104302",
            "link": "None"
        },
        {
            "wallpaper_id": "104305",
            "link": "None"
        },
        {
            "wallpaper_id": "104306",
            "link": "None"
        },
        {
            "wallpaper_id": "104307",
            "link": "None"
        },
        {
            "wallpaper_id": "104308",
            "link": "None"
        },
        {
            "wallpaper_id": "104309",
            "link": "None"
        },
        {
            "wallpaper_id": "104310",
            "link": "None"
        },
        {
            "wallpaper_id": "104311",
            "link": "None"
        },
        {
            "wallpaper_id": "104312",
            "link": "None"
        },
        {
            "wallpaper_id": "104313",
            "link": "None"
        },
        {
            "wallpaper_id": "104314",
            "link": "None"
        },
        {
            "wallpaper_id": "104380",
            "link": "None"
        },
        {
            "wallpaper_id": "104381",
            "link": "None"
        },
        {
            "wallpaper_id": "104502",
            "link": "None"
        },
        {
            "wallpaper_id": "104505",
            "link": "None"
        },
        {
            "wallpaper_id": "104506",
            "link": "None"
        },
        {
            "wallpaper_id": "104507",
            "link": "None"
        },
        {
            "wallpaper_id": "104508",
            "link": "None"
        },
        {
            "wallpaper_id": "104509",
            "link": "None"
        },
        {
            "wallpaper_id": "104510",
            "link": "None"
        },
        {
            "wallpaper_id": "104511",
            "link": "None"
        },
        {
            "wallpaper_id": "104512",
            "link": "None"
        },
        {
            "wallpaper_id": "104513",
            "link": "None"
        },
        {
            "wallpaper_id": "104514",
            "link": "None"
        },
        {
            "wallpaper_id": "104515",
            "link": "None"
        },
        {
            "wallpaper_id": "104516",
            "link": "None"
        },
        {
            "wallpaper_id": "104602",
            "link": "None"
        },
        {
            "wallpaper_id": "104605",
            "link": "None"
        },
        {
            "wallpaper_id": "104702",
            "link": "None"
        },
        {
            "wallpaper_id": "104705",
            "link": "None"
        },
        {
            "wallpaper_id": "104706",
            "link": "None"
        },
        {
            "wallpaper_id": "104707",
            "link": "None"
        },
        {
            "wallpaper_id": "104802",
            "link": "None"
        },
        {
            "wallpaper_id": "104805",
            "link": "None"
        },
        {
            "wallpaper_id": "104806",
            "link": "None"
        },
        {
            "wallpaper_id": "104807",
            "link": "None"
        },
        {
            "wallpaper_id": "104808",
            "link": "None"
        },
        {
            "wallpaper_id": "104809",
            "link": "None"
        },
        {
            "wallpaper_id": "104902",
            "link": "None"
        },
        {
            "wallpaper_id": "104905",
            "link": "None"
        },
        {
            "wallpaper_id": "104906",
            "link": "None"
        },
        {
            "wallpaper_id": "104907",
            "link": "None"
        },
        {
            "wallpaper_id": "104908",
            "link": "None"
        },
        {
            "wallpaper_id": "104909",
            "link": "None"
        },
        {
            "wallpaper_id": "104910",
            "link": "None"
        },
        {
            "wallpaper_id": "105003",
            "link": "None"
        },
        {
            "wallpaper_id": "105005",
            "link": "None"
        },
        {
            "wallpaper_id": "105006",
            "link": "None"
        },
        {
            "wallpaper_id": "105007",
            "link": "None"
        },
        {
            "wallpaper_id": "105080",
            "link": "None"
        },
        {
            "wallpaper_id": "105081",
            "link": "None"
        },
        {
            "wallpaper_id": "105102",
            "link": "None"
        },
        {
            "wallpaper_id": "105105",
            "link": "None"
        },
        {
            "wallpaper_id": "105106",
            "link": "None"
        },
        {
            "wallpaper_id": "105107",
            "link": "None"
        },
        {
            "wallpaper_id": "105204",
            "link": "None"
        },
        {
            "wallpaper_id": "105701",
            "link": "None"
        },
        {
            "wallpaper_id": "105705",
            "link": "None"
        }
    ]
}